README.rst
setup.cfg
setup.py
torchiva/__init__.py
torchiva/auxiva_ip.py
torchiva/auxiva_ip2.py
torchiva/base.py
torchiva/beamformer.py
torchiva/dtypes.py
torchiva/fftconvolve.py
torchiva/five.py
torchiva/linalg.py
torchiva/loader.py
torchiva/nn.py
torchiva/parameters.py
torchiva/scaling.py
torchiva/separate.py
torchiva/stft.py
torchiva/t_iss.py
torchiva/utils.py
torchiva/wpe.py
torchiva.egg-info/PKG-INFO
torchiva.egg-info/SOURCES.txt
torchiva.egg-info/dependency_links.txt
torchiva.egg-info/requires.txt
torchiva.egg-info/top_level.txt
torchiva/models/__init__.py
torchiva/models/blstm.py
torchiva/models/classic.py
torchiva/models/glu.py
torchiva/models/parameters.py
torchiva/models/simple.py